fst/__init__.py
fst-0.0.2.dist-info/LICENSE
fst-0.0.2.dist-info/METADATA
fst-0.0.2.dist-info/WHEEL
fst-0.0.2.dist-info/top_level.txt
fst-0.0.2.dist-info/RECORD
