Metadata-Version: 2.1
Name: fst
Version: 0.0.2
Summary: FST in Python3 - NLP
